mcp_server_tke/__init__.py
mcp_server_tke/client.py
mcp_server_tke/dynamic_tool_handler.py
mcp_server_tke/mcpapi_loader.py
mcp_server_tke/server.py
mcp_server_tke/tool_tke.py
mcp_server_tke/mcpapi/2018-05-25_DeleteCluster.yaml
mcp_server_tke/mcpapi/2018-05-25_DescribeClusters.yaml
mcp_server_tke/mcpapi/2018-05-25_ModifyClusterAttribute.yaml
mcp_server_tke-0.0.5.dist-info/METADATA
mcp_server_tke-0.0.5.dist-info/WHEEL
mcp_server_tke-0.0.5.dist-info/entry_points.txt
mcp_server_tke-0.0.5.dist-info/RECORD
