Metadata-Version: 2.4
Name: mcp-server-tke
Version: 0.0.5
Summary: MCP Server for Tencent Cloud TKE
Requires-Python: >=3.10
Requires-Dist: mcp>=1.0.0
Requires-Dist: tencentcloud-sdk-python-common==3.0.1356
Requires-Dist: tencentcloud-sdk-python-tke==3.0.1356
